OcrReqPackage/__init__.py
OcrReqPackage/ocr_req_or_not.py
OCR_Required_or_not-0.1.dist-info/LICENSE.txt
OCR_Required_or_not-0.1.dist-info/METADATA
OCR_Required_or_not-0.1.dist-info/WHEEL
OCR_Required_or_not-0.1.dist-info/top_level.txt
OCR_Required_or_not-0.1.dist-info/RECORD
