Metadata-Version: 2.1
Name: OCR-Required-or-not
Version: 0.1
Summary: An example python package
Home-page: UNKNOWN
Author: Vardhani k 
Author-email: myemail@example.com
License: MIT
Platform: UNKNOWN
License-File: LICENSE.txt
Requires-Dist: numpy
Requires-Dist: fitz
